{
  "name": "Janus",
  "cycle_count": 1,
  "current_goal": "Open Notepad and type hello",
  "timestamp": "2026-04-27T23:05:52.675477",
  "status": {
    "avus": true,
    "screen": true,
    "skills": true,
    "game": true,
    "ceo": true,
    "os": true
  },
  "last_cycle": {
    "cycle": 1,
    "timestamp": "2026-04-27T23:00:23.064787",
    "phase": "complete",
    "goal": "Open Notepad and type hello",
    "screen_desc": "A dark-themed application or terminal is open. Screen resolution: 1920x1080. A UI element at approximately (875, 446). A UI element at approximately (163, 549). A UI element at approximately (1660, 533). A UI element at approximately (1668, 924). A UI element at approximately (875, 79). The screen is predominantly dark. Current task: Open Notepad and type hello.",
    "avus_output": {},
    "action_taken": null,
    "asset_generated": true,
    "asset_name": "default_object",
    "success": true,
    "error": null,
    "duration_ms": 329610.68964004517,
    "notes": [
      "Screen: A dark-themed application or terminal is open. Screen resolution: 1920x1080. A U...",
      "Plan: Start working toward: Generate AAA Game Assets",
      "Act type: asset  output: {}",
      "Execute: {'name': 'default_object', 'prompt': 'Open Notepad and type hello', 'success': False, 'generation_ms': 165399.90544319153, 'error': 'Both geometry and texture generation failed.', 'avus_params': {'object_name': 'default_object', 'geometry': {'primitive_type': 'sphere', 'geometry_params': {'radius': 1.0, 'segments': 32}}, 'material': {'material_type': 'stone', 'material_params': {'resolution': [512, 512], 'roughness_scale': 0.7, 'metallic_scale': 0.0}}}, 'has_geometry': False, 'has_textures': False, 'texture_maps': [], 'metadata': {'avus_used': True, 'stack_used': False, 'resolution': 512}}"
    ]
  }
}